.gitignore
CHANGES.txt
CONTRIBUTORS.txt
MANIFEST.in
README.rst
bootstrap.py
buildout.cfg
setup.py
collective/__init__.py
collective.z3cform.html5widgets.egg-info/PKG-INFO
collective.z3cform.html5widgets.egg-info/SOURCES.txt
collective.z3cform.html5widgets.egg-info/dependency_links.txt
collective.z3cform.html5widgets.egg-info/entry_points.txt
collective.z3cform.html5widgets.egg-info/namespace_packages.txt
collective.z3cform.html5widgets.egg-info/not-zip-safe
collective.z3cform.html5widgets.egg-info/requires.txt
collective.z3cform.html5widgets.egg-info/top_level.txt
collective/z3cform/__init__.py
collective/z3cform/html5widgets/__init__.py
collective/z3cform/html5widgets/base.py
collective/z3cform/html5widgets/configure.zcml
collective/z3cform/html5widgets/layer.py
collective/z3cform/html5widgets/upgrades.py
collective/z3cform/html5widgets/upgrades.zcml
collective/z3cform/html5widgets/widget_color.py
collective/z3cform/html5widgets/widget_color.zcml
collective/z3cform/html5widgets/widget_contenteditable.py
collective/z3cform/html5widgets/widget_contenteditable.zcml
collective/z3cform/html5widgets/widget_datalist.py
collective/z3cform/html5widgets/widget_datalist.zcml
collective/z3cform/html5widgets/widget_date.py
collective/z3cform/html5widgets/widget_date.zcml
collective/z3cform/html5widgets/widget_datetime.py
collective/z3cform/html5widgets/widget_datetime.zcml
collective/z3cform/html5widgets/widget_datetimelocal.py
collective/z3cform/html5widgets/widget_datetimelocal.zcml
collective/z3cform/html5widgets/widget_email.py
collective/z3cform/html5widgets/widget_email.zcml
collective/z3cform/html5widgets/widget_month.py
collective/z3cform/html5widgets/widget_month.zcml
collective/z3cform/html5widgets/widget_number.py
collective/z3cform/html5widgets/widget_number.zcml
collective/z3cform/html5widgets/widget_password.py
collective/z3cform/html5widgets/widget_password.zcml
collective/z3cform/html5widgets/widget_range.py
collective/z3cform/html5widgets/widget_range.zcml
collective/z3cform/html5widgets/widget_search.py
collective/z3cform/html5widgets/widget_search.zcml
collective/z3cform/html5widgets/widget_tel.py
collective/z3cform/html5widgets/widget_tel.zcml
collective/z3cform/html5widgets/widget_time.py
collective/z3cform/html5widgets/widget_time.zcml
collective/z3cform/html5widgets/widget_url.py
collective/z3cform/html5widgets/widget_url.zcml
collective/z3cform/html5widgets/widget_week.py
